gwt_test_framework/__init__.py
gwt_test_framework/base.py
gwt_test_framework-0.1.1.dist-info/METADATA
gwt_test_framework-0.1.1.dist-info/WHEEL
gwt_test_framework-0.1.1.dist-info/top_level.txt
gwt_test_framework-0.1.1.dist-info/RECORD
