Metadata-Version: 2.1
Name: gwt-test-framework
Version: 0.1.1
Summary: A Python framework for declaring Given-When-Then tests
Requires-Python: >=3.10
Provides-Extra: dev
Requires-Dist: pre-commit>=4.0.1; extra == "dev"
Requires-Dist: pytest>=8.3.4; extra == "dev"
Requires-Dist: ruff>=0.8.4; extra == "dev"
